macopt/__init__.py
macopt/macopt.py
tests/__init__.py
tests/test_macopt.py
macopt-0.0.1.dist-info/LICENSE
macopt-0.0.1.dist-info/METADATA
macopt-0.0.1.dist-info/WHEEL
macopt-0.0.1.dist-info/top_level.txt
macopt-0.0.1.dist-info/RECORD
